{
  "version": 2,
  "extractor": "papercropper",
  "tables": [
    {
      "url": "assets/tables/arxiv/2607.09424v2/table-001.webp",
      "caption": "",
      "page": 0,
      "index": 1,
      "width": 1241,
      "height": 1097,
      "label": "Table"
    },
    {
      "url": "assets/tables/arxiv/2607.09424v2/table-002.webp",
      "caption": "",
      "page": 0,
      "index": 2,
      "width": 1625,
      "height": 380,
      "label": "Table"
    },
    {
      "url": "assets/tables/arxiv/2607.09424v2/table-003.webp",
      "caption": "",
      "page": 0,
      "index": 3,
      "width": 1308,
      "height": 334,
      "label": "Table"
    },
    {
      "url": "assets/tables/arxiv/2607.09424v2/table-004.webp",
      "caption": "",
      "page": 0,
      "index": 4,
      "width": 1065,
      "height": 1832,
      "label": "Table"
    },
    {
      "url": "assets/tables/arxiv/2607.09424v2/table-005.webp",
      "caption": "",
      "page": 0,
      "index": 5,
      "width": 1276,
      "height": 1753,
      "label": "Table"
    },
    {
      "url": "assets/tables/arxiv/2607.09424v2/table-006.webp",
      "caption": "",
      "page": 0,
      "index": 6,
      "width": 1703,
      "height": 1676,
      "label": "Table"
    },
    {
      "url": "assets/tables/arxiv/2607.09424v2/table-007.webp",
      "caption": "",
      "page": 0,
      "index": 7,
      "width": 1275,
      "height": 870,
      "label": "Table"
    },
    {
      "url": "assets/tables/arxiv/2607.09424v2/table-008.webp",
      "caption": "",
      "page": 0,
      "index": 8,
      "width": 1706,
      "height": 1037,
      "label": "Table"
    },
    {
      "url": "assets/tables/arxiv/2607.09424v2/table-009.webp",
      "caption": "",
      "page": 0,
      "index": 9,
      "width": 1710,
      "height": 2136,
      "label": "Table"
    },
    {
      "url": "assets/tables/arxiv/2607.09424v2/table-010.webp",
      "caption": "",
      "page": 0,
      "index": 10,
      "width": 1712,
      "height": 1660,
      "label": "Table"
    },
    {
      "url": "assets/tables/arxiv/2607.09424v2/table-011.webp",
      "caption": "",
      "page": 0,
      "index": 11,
      "width": 1313,
      "height": 776,
      "label": "Table"
    },
    {
      "url": "assets/tables/arxiv/2607.09424v2/table-012.webp",
      "caption": "",
      "page": 0,
      "index": 12,
      "width": 1399,
      "height": 564,
      "label": "Table"
    },
    {
      "url": "assets/tables/arxiv/2607.09424v2/table-013.webp",
      "caption": "",
      "page": 0,
      "index": 13,
      "width": 1913,
      "height": 550,
      "label": "Table"
    },
    {
      "url": "assets/tables/arxiv/2607.09424v2/table-014.webp",
      "caption": "",
      "page": 0,
      "index": 14,
      "width": 1711,
      "height": 501,
      "label": "Table"
    },
    {
      "url": "assets/tables/arxiv/2607.09424v2/table-015.webp",
      "caption": "",
      "page": 0,
      "index": 15,
      "width": 1134,
      "height": 628,
      "label": "Table"
    },
    {
      "url": "assets/tables/arxiv/2607.09424v2/table-016.webp",
      "caption": "",
      "page": 0,
      "index": 16,
      "width": 1084,
      "height": 667,
      "label": "Table"
    },
    {
      "url": "assets/tables/arxiv/2607.09424v2/table-017.webp",
      "caption": "",
      "page": 0,
      "index": 17,
      "width": 1681,
      "height": 1582,
      "label": "Table"
    },
    {
      "url": "assets/tables/arxiv/2607.09424v2/table-018.webp",
      "caption": "",
      "page": 0,
      "index": 18,
      "width": 1702,
      "height": 499,
      "label": "Table"
    }
  ]
}